PoroPilot/PoroPilot.py
PoroPilot/RequestHandler.py
PoroPilot/__init__.py
PoroPilot/Endpoints/__init__.py
PoroPilot/Endpoints/account_v1.py
PoroPilot/Endpoints/championMastery_v4.py
PoroPilot/Endpoints/champion_v3.py
PoroPilot/Endpoints/leagueExp_v4.py
PoroPilot/Endpoints/league_v4.py
PoroPilot/Endpoints/lolStatus_v4.py
PoroPilot/Endpoints/match_v5.py
PoroPilot/Endpoints/spectator_v5.py
PoroPilot/Endpoints/summoner_v4.py
PoroPilot-0.2.10.dist-info/METADATA
PoroPilot-0.2.10.dist-info/WHEEL
PoroPilot-0.2.10.dist-info/top_level.txt
PoroPilot-0.2.10.dist-info/RECORD
