Metadata-Version: 2.1
Name: PoroPilot
Version: 0.2.10
Summary: Wrapper Interface for Riot API
Home-page: https://github.com/anuiit/PoroPilot
Author: anuiit
Author-email: 
License: MIT
Keywords: Riot,API,wrapper,Poro,Pilot,League of Legends,LoL,game,gaming,esports,riotgames,riot-api,riot-api-wrapper,riot-api-python,riot-api
Requires-Dist: requests
Requires-Dist: requests-cache
